<?xml version="1.0" encoding="UTF-8" ?>
<usergroup xmlns:xsi="http://www.w3.org/2001/XMLSchema-instance"
           xsi:noNamespaceSchemaLocation="../xsd/usergroup.xsd">
    <name>Python UserGroup RheinMain</name>
    <nickname>PyUGRM</nickname>
    <description>Pythonistas aus dem Rhein-Main-Gebiet treffen sich alle
        zwei Monate an wechselnden Locations im
        Rhein-Main-Gebiet.
        Ruby-Entwickler sind ebenfalls herzlich eingeladen.
    </description>
    <url>http://wiki.python-forum.de/PyUGRM</url>
    <tags>
        <tag>Python</tag>
        <tag>Ruby</tag>
    </tags>
    <contact>
        <mailinglist>
            <url>http://groups.google.com/group/pyugrm</url>
            <label>Mailingliste</label>
            <description>zum Austausch von Mitgliedern und Interessierten
            </description>
        </mailinglist>
        <mailinglist>
            <url>http://groups.google.com/group/pyugrm-orga</url>
            <label>Orga-Mailingliste</label>
            <description>nur für Termine und Organisatorisches, moderiert
            </description>
        </mailinglist>
        <twitter>@PyUGRM</twitter>
        <hashtag>#PyUGRM</hashtag>
    </contact>
    <schedule>
        <!-- Entweder ical-Feed angeben oder Meetings manuell eintragen -->
        <!-- ical> https://www.google.com/calendar/ical/q408a75de70rb2ebqka3i18nc0%40group.calendar.google.com/public/basic.ics
            </ical -->
        <meeting>
            <time>2013-09-19T19:00:00+02:00</time>
            <name>9 . Treffen der PyUGRM</name>
            <url>http://wiki.python-forum.de/PyUGRM/Treffen20130919</url>
            <location>
                <name>Brot &amp; Spiele GmbH</name>
                <street>Benzstr. 11</street>
                <zip>61352</zip>
                <city>Bad Homburg</city>
            </location>
        </meeting>
        <meeting>
            <time>2013-08-20T19:00:00+02:00</time>
            <name>8. Treffen der PyUGRM</name>
            <url>http://wiki.python-forum.de/PyUGRM/Treffen20130820</url>
            <location>
                <name>Brot &amp; Spiele GmbH</name>
                <street>Benzstr. 11</street>
                <zip>61352</zip>
                <city>Bad Homburg</city>
            </location>
        </meeting> 
        <meeting>
            <time>2013-06-20T19:00:00+02:00</time>
            <name>7. Treffen der PyUGRM</name>
            <url>http://wiki.python-forum.de/PyUGRM/Treffen20130620</url>
            <location>
                <name>Trollhöhle des Chaos Darmstadt</name>
                <url>https://wiki.chaos-darmstadt.de/wiki/Trollh%C3%B6hle</url>
                <foursquare>https://foursquare.com/v/trollh%C3%B6hle/5155a0e7e4b0d9a3f3dcde86</foursquare>
                <twitter>@chaosdarmstadt</twitter>
                <street>Wilhelm-Leuschner-Straße 36</street>
                <zip>64293</zip>
                <city>Darmstadt</city>
            </location>
        </meeting>
        <meeting>
            <time>2013-03-20T19:00:00+01:00</time>
            <name>6. Treffen der PyUGRM</name>
            <url>http://wiki.python-forum.de/PyUGRM/Treffen20130320</url>
            <location>
                <name>arago Institut für komplexes Datenmanagement AG</name>
                <url>http://www.arago.de/</url>
                <publictransport>U1, U2, U3, U8 Weißer Stein, S6 Frankfurt-Eschenheim</publictransport>
                <street>Eschersheimer Landstrasse 526–532</street>
                <zip>60433</zip>
                <city>Frankfurt</city>
            </location>
        </meeting>
        <meeting>
            <time>2012-05-08T19:00:00+02:00</time>
            <name>1. Treffen der PyUGRM</name>
            <url>http://wiki.python-forum.de/PyUGRM/Treffen20120508</url>
            <location>
                <name>Brot &amp; Spiele GmbH</name>
                <street>Benzstr. 11</street>
                <zip>61352</zip>
                <city>Bad Homburg</city>
            </location>
        </meeting>
        <meeting>
            <time>2012-07-18T19:00:00+02:00</time>
            <name>2. Treffen der PyUGRM</name>
            <url>http://wiki.python-forum.de/PyUGRM/Treffen20120718</url>
            <location>
                <name>Bürogemeinschaft paratio.com e.K.</name>
                <street>Gr. Eschenheimer Str. 41a</street>
                <zip>60313</zip>
                <city>Frankfurt</city>
            </location>
        </meeting>
        <meeting>
            <time>2012-09-20T19:00:00+02:00</time>
            <name>3. Treffen der PyUGRM</name>
            <url>http://wiki.python-forum.de/PyUGRM/Treffen20120920</url>
            <location>
                <name>Campus Westend</name>
                <description>Auf dem CloudOps Summit 2012</description>
                <url>http://cloudops.de/cloudops-2012/</url>
                <street>Senckenberganlage 31</street>
                <zip>60325</zip>
                <city>Frankfurt</city>
            </location>
        </meeting>
        <meeting>
            <time>2012-11-22T19:00:00+01:00</time>
            <name>4. Treffen der PyUGRM</name>
            <url>http://wiki.python-forum.de/PyUGRM/Treffen20121122</url>
            <location>
                <name>OFfenraum coworking space</name>
                <description>Der OFfenraum ist der erste unabhängige, inhabergeführte Coworking Space in Offenbach am
                    Main.
                </description>
                <url>http://offenraum.de/#lage</url>
                <foursquare>https://de.foursquare.com/offenraum</foursquare>
                <twitter>@OFfenraum</twitter>
                <publictransport>Regionalbahn HBf Offenbach. S1, S2, S8,
                    S9 Offenbach Markplatz. Bus 104 Haydnstraße.
                </publictransport>
                <street>Senefelderstr. 63</street>
                <zip>63069</zip>
                <city>Offenbach am Main</city>
            </location>
        </meeting>
        <meeting>
            <time>2013-01-16T19:00:00+01:00</time>
            <name>5. Treffen der PyUGRM</name>
            <url>http://wiki.python-forum.de/PyUGRM/Treffen20130116</url>
            <location>
                <name>Die Zentrale</name>
                <description>Coworking in Frankfurt. Echt jetzt. Nein, wirklich. Wir sind kein Business
                    Center. Wir haben nicht nur Schreibtische und Wlan zu vermieten.
                </description>
                <url>http://www.die-zentrale-ffm.de/#section-n6</url>
                <foursquare>https://de.foursquare.com/zentrale_ffm</foursquare>
                <twitter>@zentrale_ffm</twitter>
                <publictransport>U4, Tram 12, Bus 34 Bornheim Mitte</publictransport>
                <street>Berger Straße 175</street>
                <zip>60385</zip>
                <city>Frankfurt</city>
            </location>
        </meeting>
    </schedule>
    <team>
        <person>
            <name>Stefan Antoni</name>
            <url>http://stefan.antoni.io/</url>
            <email>stefan@antoni.io</email>
            <twitter>@suchkultur</twitter>
        </person>
        <person>
            <name>Ulrich Petri</name>
            <twitter>@ulope</twitter>
        </person>
    </team>
    <sponsors>
        <sponsor>
            <name>Walter Ebert</name>
            <url>http://www.walterebert.de/</url>
        </sponsor>
        <sponsor>
            <name>Brot &amp; Spiele GmbH</name>
            <url>http://spieletipps.de/</url>
        </sponsor>
        <sponsor>
            <name>arago Institut für komplexes Datenmanagement AG</name>
            <url>http://www.arago.de/</url>
        </sponsor>
        <sponsor>
            <name>OFfenraum · coworking space</name>
            <url>http://offenraum.de/</url>
        </sponsor>
        <sponsor>
            <name>Die Zentrale</name>
            <url>http://die-zentrale-ffm.de/</url>
        </sponsor>
    </sponsors>
    <photocredits>
        <logo>Das Python-Logo stammt aus dem [Tango-Projekt](http://tango.freedesktop.org/).</logo>
        <group>Foto: Lukas Koerdt.</group>
    </photocredits>
</usergroup>
